raftkit/__init__.py
raftkit/raftkit.py
raftkit/udp.py
raftkit-0.1.0.dist-info/DESCRIPTION.rst
raftkit-0.1.0.dist-info/METADATA
raftkit-0.1.0.dist-info/RECORD
raftkit-0.1.0.dist-info/WHEEL
raftkit-0.1.0.dist-info/metadata.json
raftkit-0.1.0.dist-info/top_level.txt
