Metadata-Version: 2.0
Name: raftkit
Version: 0.1.0
Summary: raftkit
Home-page: https://github.com/xhs/raftkit
Author: xhs
Author-email: chef@dark.kitchen
License: UNKNOWN
Platform: UNKNOWN
Classifier: Programming Language :: Python :: 3
Requires-Dist: docopt
Requires-Dist: structlog
